moj_elektro_v1/__init__.py
moj_elektro_v1/py.typed
moj_elektro_v1/blocks/__init__.py
moj_elektro_v1/blocks/time_blocks.json
moj_elektro_v1/blocks/time_blocks.py
moj_elektro_v1/http_access/__init__.py
moj_elektro_v1/http_access/http_JSON_conn.py
moj_elektro_v1/web_api_access/__init__.py
moj_elektro_v1/web_api_access/merilna_tocka.py
moj_elektro_v1/web_api_access/merilno_mesto.py
moj_elektro_v1/web_api_access/meter_quailities.py
moj_elektro_v1/web_api_access/meter_readings.py
moj_elektro_v1/web_api_access/meter_type.py
moj_elektro_v1-0.0.2.dist-info/LICENSE
moj_elektro_v1-0.0.2.dist-info/METADATA
moj_elektro_v1-0.0.2.dist-info/WHEEL
moj_elektro_v1-0.0.2.dist-info/top_level.txt
moj_elektro_v1-0.0.2.dist-info/RECORD
